LICENSE
MANIFEST.in
README.md
pyproject.toml
setup.py
zx.h
test/__init__.py
test/test_api.py
test/test_roms.py
test/test_spectrum48.py
test/screen_timing/generate_drawing.py
tests/test_data.py
tests/test_emulator.py
tests/test_rzx.py
tests/test_scr.py
tests/test_tap.py
tests/test_tzx.py
tests/test_wav.py
tests/test_z80snapshot.py
z80/z80.h
zx/__init__.py
zx/__main__.py
zx/_beeper.py
zx/_binary.py
zx/_data.py
zx/_device.py
zx/_error.py
zx/_except.py
zx/_file.py
zx/_gamepad.py
zx/_keyboard.py
zx/_main.py
zx/_playback.py
zx/_rom.py
zx/_rzx.py
zx/_scr.py
zx/_screen.py
zx/_sound.py
zx/_spectrum.py
zx/_spectrumbase.cpp
zx/_spectrumbase.pyi
zx/_tap.py
zx/_tape.py
zx/_time.py
zx/_tzx.py
zx/_utils.py
zx/_wav.py
zx/_z80snapshot.py
zx/_zip.py
zx/_zxb.py
zx/py.typed
zx.egg-info/PKG-INFO
zx.egg-info/SOURCES.txt
zx.egg-info/dependency_links.txt
zx.egg-info/entry_points.txt
zx.egg-info/requires.txt
zx.egg-info/top_level.txt
zx/roms/Spectrum48.rom