Metadata-Version: 2.4
Name: zx
Version: 0.12.0
Summary: ZX Spectrum emulation framework
Home-page: https://github.com/kosarev/zx/
Author: Ivan Kosarev
Author-email: Ivan Kosarev <mail@ivankosarev.com>
License: MIT
Project-URL: Homepage, https://github.com/kosarev/zx/
Requires-Python: >=3.7
License-File: LICENSE
Requires-Dist: pysdl2
Requires-Dist: pysdl2-dll
Requires-Dist: numpy
Requires-Dist: evdev; sys_platform == "linux"
Dynamic: author
Dynamic: home-page
Dynamic: license-file
